Catsh/__init__.py
Catsh/config.py
Catsh/main.py
Catsh/commands/Clean.py
Catsh/commands/Close.py
Catsh/commands/Env.py
Catsh/commands/Exec.py
Catsh/commands/Print.py
Catsh/commands/__init__.py
Catsh/utils/Error.py
Catsh/utils/Warning.py
Catsh/utils/__init__.py
catsh-0.1.10.dist-info/LICENSE
catsh-0.1.10.dist-info/METADATA
catsh-0.1.10.dist-info/WHEEL
catsh-0.1.10.dist-info/entry_points.txt
catsh-0.1.10.dist-info/top_level.txt
catsh-0.1.10.dist-info/RECORD
