Metadata-Version: 2.1
Name: catsh
Version: 0.1.10
Summary: A cross-platform shell write in python
Home-page: https://github.com/JheysonDev/catsh
Author: JheysonDev
License: GPLv3
Platform: UNKNOWN
Classifier: Environment :: Console
Classifier: Programming Language :: Python :: 3
Classifier: Operating System :: OS Independent
Classifier: License :: OSI Approved :: GNU General Public License v3 (GPLv3)
Requires-Python: >=3.6
Requires-Dist: colorama (==0.4.4)
